BICAMSZ/__init__.py
BICAMSZ/functions.py
BICAMSZ-1.0.5.dist-info/LICENSE
BICAMSZ-1.0.5.dist-info/METADATA
BICAMSZ-1.0.5.dist-info/WHEEL
BICAMSZ-1.0.5.dist-info/top_level.txt
BICAMSZ-1.0.5.dist-info/RECORD
