Metadata-Version: 2.1
Name: BICAMSZ
Version: 1.0.5
Summary: Tools to convert BICAMS scores to z scores in a Belgian (Dutch) population
Home-page: https://github.com/sdniss/BICAMSZ
Author: Stijn Denissen
Author-email: stijndenissen94@gmail.com
License: MIT License
License-File: LICENSE
Requires-Dist: numpy
Requires-Dist: pandas
